color_processing/__init__.py
color_processing/colors.py
color_processing/models.py
color_processing/data/colors.pkl
color_processing-1.1.dist-info/METADATA
color_processing-1.1.dist-info/WHEEL
color_processing-1.1.dist-info/top_level.txt
color_processing-1.1.dist-info/RECORD
