Metadata-Version: 2.1
Name: color_processing
Version: 1.1
Summary: A package for fetching detailed color information
Home-page: https://github.com/cop-discord/color_processing
Author: cop-discord
Author-email: cop@catgir.ls
Classifier: Programming Language :: Python :: 3
Classifier: License :: OSI Approved :: MIT License
Classifier: Operating System :: OS Independent
Requires-Python: >=3.6
Requires-Dist: discord
Requires-Dist: fast-string-match
Requires-Dist: seaborn
Requires-Dist: numpy
Requires-Dist: webcolors
Requires-Dist: colorgram-rs
Requires-Dist: async-tools-ext
